{"nodes": [{"id": "assets_playfabeditorextensions_editor_scripts_utils_editorcoroutine_cs", "label": "EditorCoroutine.cs", "file_type": "code", "type": "FUNCTION", "source_file": "Assets\\PlayFabEditorExtensions\\Editor\\Scripts\\Utils\\EditorCoroutine.cs", "source_location": "L1", "complexity": 1, "loc": 1}, {"id": "editorcoroutine_playfab_pfeditor", "label": "PlayFab.PfEditor", "file_type": "code", "type": "FUNCTION", "source_file": "Assets\\PlayFabEditorExtensions\\Editor\\Scripts\\Utils\\EditorCoroutine.cs", "source_location": "L8", "complexity": 1, "loc": 1}, {"id": "editorcoroutine_editorcoroutine", "label": "EditorCoroutine", "file_type": "code", "type": "CLASS", "source_file": "Assets\\PlayFabEditorExtensions\\Editor\\Scripts\\Utils\\EditorCoroutine.cs", "source_location": "L10", "complexity": 17, "loc": 135}, {"id": "editorcoroutine_editorwaitforseconds", "label": "EditorWaitForSeconds", "file_type": "code", "type": "CLASS", "source_file": "Assets\\PlayFabEditorExtensions\\Editor\\Scripts\\Utils\\EditorCoroutine.cs", "source_location": "L13", "complexity": 1, "loc": 9}, {"id": "yieldinstruction", "label": "YieldInstruction", "file_type": "code", "source_file": "", "source_location": ""}, {"id": "editorcoroutine_editorcoroutine_start", "label": ".Start()", "file_type": "code", "type": "FUNCTION", "source_file": "Assets\\PlayFabEditorExtensions\\Editor\\Scripts\\Utils\\EditorCoroutine.cs", "source_location": "L26", "complexity": 1, "loc": 7}, {"id": "editorcoroutine_start", "label": "Start()", "file_type": "code", "type": "FUNCTION", "source_file": "Assets\\PlayFabEditorExtensions\\Editor\\Scripts\\Utils\\EditorCoroutine.cs", "source_location": "L35", "complexity": 1, "loc": 8}, {"id": "editorcoroutine_editorcoroutine_stop", "label": ".Stop()", "file_type": "code", "type": "FUNCTION", "source_file": "Assets\\PlayFabEditorExtensions\\Editor\\Scripts\\Utils\\EditorCoroutine.cs", "source_location": "L74", "complexity": 1, "loc": 5}, {"id": "editorcoroutine_editorcoroutine_update", "label": ".Update()", "file_type": "code", "type": "FUNCTION", "source_file": "Assets\\PlayFabEditorExtensions\\Editor\\Scripts\\Utils\\EditorCoroutine.cs", "source_location": "L81", "complexity": 17, "loc": 63}], "edges": [{"source": "assets_playfabeditorextensions_editor_scripts_utils_editorcoroutine_cs", "target": "system", "relation": "imports", "confidence": "EXTRACTED", "source_file": "Assets\\PlayFabEditorExtensions\\Editor\\Scripts\\Utils\\EditorCoroutine.cs", "source_location": "L1", "weight": 1.0}, {"source": "assets_playfabeditorextensions_editor_scripts_utils_editorcoroutine_cs", "target": "collections", "relation": "imports", "confidence": "EXTRACTED", "source_file": "Assets\\PlayFabEditorExtensions\\Editor\\Scripts\\Utils\\EditorCoroutine.cs", "source_location": "L2", "weight": 1.0}, {"source": "assets_playfabeditorextensions_editor_scripts_utils_editorcoroutine_cs", "target": "generic", "relation": "imports", "confidence": "EXTRACTED", "source_file": "Assets\\PlayFabEditorExtensions\\Editor\\Scripts\\Utils\\EditorCoroutine.cs", "source_location": "L3", "weight": 1.0}, {"source": "assets_playfabeditorextensions_editor_scripts_utils_editorcoroutine_cs", "target": "unityeditor", "relation": "imports", "confidence": "EXTRACTED", "source_file": "Assets\\PlayFabEditorExtensions\\Editor\\Scripts\\Utils\\EditorCoroutine.cs", "source_location": "L4", "weight": 1.0}, {"source": "assets_playfabeditorextensions_editor_scripts_utils_editorcoroutine_cs", "target": "unityengine", "relation": "imports", "confidence": "EXTRACTED", "source_file": "Assets\\PlayFabEditorExtensions\\Editor\\Scripts\\Utils\\EditorCoroutine.cs", "source_location": "L5", "weight": 1.0}, {"source": "assets_playfabeditorextensions_editor_scripts_utils_editorcoroutine_cs", "target": "networking", "relation": "imports", "confidence": "EXTRACTED", "source_file": "Assets\\PlayFabEditorExtensions\\Editor\\Scripts\\Utils\\EditorCoroutine.cs", "source_location": "L6", "weight": 1.0}, {"source": "assets_playfabeditorextensions_editor_scripts_utils_editorcoroutine_cs", "target": "editorcoroutine_playfab_pfeditor", "relation": "contains", "confidence": "EXTRACTED", "source_file": "Assets\\PlayFabEditorExtensions\\Editor\\Scripts\\Utils\\EditorCoroutine.cs", "source_location": "L8", "weight": 1.0}, {"source": "assets_playfabeditorextensions_editor_scripts_utils_editorcoroutine_cs", "target": "editorcoroutine_editorcoroutine", "relation": "contains", "confidence": "EXTRACTED", "source_file": "Assets\\PlayFabEditorExtensions\\Editor\\Scripts\\Utils\\EditorCoroutine.cs", "source_location": "L10", "weight": 1.0}, {"source": "assets_playfabeditorextensions_editor_scripts_utils_editorcoroutine_cs", "target": "editorcoroutine_editorwaitforseconds", "relation": "contains", "confidence": "EXTRACTED", "source_file": "Assets\\PlayFabEditorExtensions\\Editor\\Scripts\\Utils\\EditorCoroutine.cs", "source_location": "L13", "weight": 1.0}, {"source": "editorcoroutine_editorwaitforseconds", "target": "yieldinstruction", "relation": "inherits", "confidence": "EXTRACTED", "source_file": "Assets\\PlayFabEditorExtensions\\Editor\\Scripts\\Utils\\EditorCoroutine.cs", "source_location": "L13", "weight": 1.0}, {"source": "editorcoroutine_editorcoroutine", "target": "editorcoroutine_editorcoroutine_start", "relation": "method", "confidence": "EXTRACTED", "source_file": "Assets\\PlayFabEditorExtensions\\Editor\\Scripts\\Utils\\EditorCoroutine.cs", "source_location": "L26", "weight": 1.0}, {"source": "assets_playfabeditorextensions_editor_scripts_utils_editorcoroutine_cs", "target": "editorcoroutine_start", "relation": "contains", "confidence": "EXTRACTED", "source_file": "Assets\\PlayFabEditorExtensions\\Editor\\Scripts\\Utils\\EditorCoroutine.cs", "source_location": "L35", "weight": 1.0}, {"source": "assets_playfabeditorextensions_editor_scripts_utils_editorcoroutine_cs", "target": "editorcoroutine_start", "relation": "contains", "confidence": "EXTRACTED", "source_file": "Assets\\PlayFabEditorExtensions\\Editor\\Scripts\\Utils\\EditorCoroutine.cs", "source_location": "L44", "weight": 1.0}, {"source": "editorcoroutine_editorcoroutine", "target": "editorcoroutine_editorcoroutine_start", "relation": "method", "confidence": "EXTRACTED", "source_file": "Assets\\PlayFabEditorExtensions\\Editor\\Scripts\\Utils\\EditorCoroutine.cs", "source_location": "L70", "weight": 1.0}, {"source": "editorcoroutine_editorcoroutine", "target": "editorcoroutine_editorcoroutine_stop", "relation": "method", "confidence": "EXTRACTED", "source_file": "Assets\\PlayFabEditorExtensions\\Editor\\Scripts\\Utils\\EditorCoroutine.cs", "source_location": "L74", "weight": 1.0}, {"source": "editorcoroutine_editorcoroutine", "target": "editorcoroutine_editorcoroutine_update", "relation": "method", "confidence": "EXTRACTED", "source_file": "Assets\\PlayFabEditorExtensions\\Editor\\Scripts\\Utils\\EditorCoroutine.cs", "source_location": "L81", "weight": 1.0}, {"source": "editorcoroutine_editorcoroutine_start", "target": "editorcoroutine_start", "relation": "calls", "confidence": "EXTRACTED", "source_file": "Assets\\PlayFabEditorExtensions\\Editor\\Scripts\\Utils\\EditorCoroutine.cs", "source_location": "L30", "weight": 1.0}, {"source": "editorcoroutine_editorcoroutine_update", "target": "editorcoroutine_editorcoroutine_stop", "relation": "calls", "confidence": "EXTRACTED", "source_file": "Assets\\PlayFabEditorExtensions\\Editor\\Scripts\\Utils\\EditorCoroutine.cs", "source_location": "L106", "weight": 1.0}], "raw_calls": [{"caller_nid": "editorcoroutine_editorcoroutine_start", "callee": "ToString", "source_file": "Assets\\PlayFabEditorExtensions\\Editor\\Scripts\\Utils\\EditorCoroutine.cs", "source_location": "L29"}, {"caller_nid": "editorcoroutine_editorcoroutine_start", "callee": "NewGuid", "source_file": "Assets\\PlayFabEditorExtensions\\Editor\\Scripts\\Utils\\EditorCoroutine.cs", "source_location": "L29"}, {"caller_nid": "editorcoroutine_start", "callee": "ToString", "source_file": "Assets\\PlayFabEditorExtensions\\Editor\\Scripts\\Utils\\EditorCoroutine.cs", "source_location": "L38"}, {"caller_nid": "editorcoroutine_start", "callee": "NewGuid", "source_file": "Assets\\PlayFabEditorExtensions\\Editor\\Scripts\\Utils\\EditorCoroutine.cs", "source_location": "L38"}, {"caller_nid": "editorcoroutine_start", "callee": "ToString", "source_file": "Assets\\PlayFabEditorExtensions\\Editor\\Scripts\\Utils\\EditorCoroutine.cs", "source_location": "L47"}, {"caller_nid": "editorcoroutine_start", "callee": "NewGuid", "source_file": "Assets\\PlayFabEditorExtensions\\Editor\\Scripts\\Utils\\EditorCoroutine.cs", "source_location": "L47"}, {"caller_nid": "editorcoroutine_editorcoroutine_stop", "callee": "Dispose", "source_file": "Assets\\PlayFabEditorExtensions\\Editor\\Scripts\\Utils\\EditorCoroutine.cs", "source_location": "L77"}, {"caller_nid": "editorcoroutine_editorcoroutine_update", "callee": "MoveNext", "source_file": "Assets\\PlayFabEditorExtensions\\Editor\\Scripts\\Utils\\EditorCoroutine.cs", "source_location": "L95"}, {"caller_nid": "editorcoroutine_editorcoroutine_update", "callee": "MoveNext", "source_file": "Assets\\PlayFabEditorExtensions\\Editor\\Scripts\\Utils\\EditorCoroutine.cs", "source_location": "L104"}, {"caller_nid": "editorcoroutine_editorcoroutine_update", "callee": "Add", "source_file": "Assets\\PlayFabEditorExtensions\\Editor\\Scripts\\Utils\\EditorCoroutine.cs", "source_location": "L115"}, {"caller_nid": "editorcoroutine_editorcoroutine_update", "callee": "MoveNext", "source_file": "Assets\\PlayFabEditorExtensions\\Editor\\Scripts\\Utils\\EditorCoroutine.cs", "source_location": "L117"}, {"caller_nid": "editorcoroutine_editorcoroutine_update", "callee": "RemoveAt", "source_file": "Assets\\PlayFabEditorExtensions\\Editor\\Scripts\\Utils\\EditorCoroutine.cs", "source_location": "L130"}, {"caller_nid": "editorcoroutine_editorcoroutine_update", "callee": "MoveNext", "source_file": "Assets\\PlayFabEditorExtensions\\Editor\\Scripts\\Utils\\EditorCoroutine.cs", "source_location": "L131"}, {"caller_nid": "editorcoroutine_editorcoroutine_update", "callee": "LogException", "source_file": "Assets\\PlayFabEditorExtensions\\Editor\\Scripts\\Utils\\EditorCoroutine.cs", "source_location": "L141"}]}