{"nodes": [{"id": "assets_playfabsdk_groups_playfabgroupsapi_cs", "label": "PlayFabGroupsAPI.cs", "file_type": "code", "type": "FUNCTION", "source_file": "Assets\\PlayFabSDK\\Groups\\PlayFabGroupsAPI.cs", "source_location": "L1", "complexity": 1, "loc": 1}, {"id": "playfabgroupsapi_playfab", "label": "PlayFab", "file_type": "code", "type": "FUNCTION", "source_file": "Assets\\PlayFabSDK\\Groups\\PlayFabGroupsAPI.cs", "source_location": "L8", "complexity": 1, "loc": 1}, {"id": "playfabgroupsapi_playfabgroupsapi", "label": "PlayFabGroupsAPI", "file_type": "code", "type": "CLASS", "source_file": "Assets\\PlayFabSDK\\Groups\\PlayFabGroupsAPI.cs", "source_location": "L15", "complexity": 101, "loc": 349}, {"id": "playfabgroupsapi_playfabgroupsapi_isentityloggedin", "label": ".IsEntityLoggedIn()", "file_type": "code", "type": "FUNCTION", "source_file": "Assets\\PlayFabSDK\\Groups\\PlayFabGroupsAPI.cs", "source_location": "L23", "complexity": 1, "loc": 4}, {"id": "playfabgroupsapi_playfabgroupsapi_forgetallcredentials", "label": ".ForgetAllCredentials()", "file_type": "code", "type": "FUNCTION", "source_file": "Assets\\PlayFabSDK\\Groups\\PlayFabGroupsAPI.cs", "source_location": "L32", "complexity": 1, "loc": 4}, {"id": "playfabgroupsapi_playfabgroupsapi_acceptgroupapplication", "label": ".AcceptGroupApplication()", "file_type": "code", "type": "FUNCTION", "source_file": "Assets\\PlayFabSDK\\Groups\\PlayFabGroupsAPI.cs", "source_location": "L40", "complexity": 5, "loc": 9}, {"id": "playfabgroupsapi_playfabgroupsapi_acceptgroupinvitation", "label": ".AcceptGroupInvitation()", "file_type": "code", "type": "FUNCTION", "source_file": "Assets\\PlayFabSDK\\Groups\\PlayFabGroupsAPI.cs", "source_location": "L53", "complexity": 5, "loc": 9}, {"id": "playfabgroupsapi_playfabgroupsapi_addmembers", "label": ".AddMembers()", "file_type": "code", "type": "FUNCTION", "source_file": "Assets\\PlayFabSDK\\Groups\\PlayFabGroupsAPI.cs", "source_location": "L66", "complexity": 5, "loc": 9}, {"id": "playfabgroupsapi_playfabgroupsapi_applytogroup", "label": ".ApplyToGroup()", "file_type": "code", "type": "FUNCTION", "source_file": "Assets\\PlayFabSDK\\Groups\\PlayFabGroupsAPI.cs", "source_location": "L79", "complexity": 5, "loc": 9}, {"id": "playfabgroupsapi_playfabgroupsapi_blockentity", "label": ".BlockEntity()", "file_type": "code", "type": "FUNCTION", "source_file": "Assets\\PlayFabSDK\\Groups\\PlayFabGroupsAPI.cs", "source_location": "L92", "complexity": 5, "loc": 9}, {"id": "playfabgroupsapi_playfabgroupsapi_changememberrole", "label": ".ChangeMemberRole()", "file_type": "code", "type": "FUNCTION", "source_file": "Assets\\PlayFabSDK\\Groups\\PlayFabGroupsAPI.cs", "source_location": "L105", "complexity": 5, "loc": 9}, {"id": "playfabgroupsapi_playfabgroupsapi_creategroup", "label": ".CreateGroup()", "file_type": "code", "type": "FUNCTION", "source_file": "Assets\\PlayFabSDK\\Groups\\PlayFabGroupsAPI.cs", "source_location": "L118", "complexity": 5, "loc": 9}, {"id": "playfabgroupsapi_playfabgroupsapi_createrole", "label": ".CreateRole()", "file_type": "code", "type": "FUNCTION", "source_file": "Assets\\PlayFabSDK\\Groups\\PlayFabGroupsAPI.cs", "source_location": "L131", "complexity": 5, "loc": 9}, {"id": "playfabgroupsapi_playfabgroupsapi_deletegroup", "label": ".DeleteGroup()", "file_type": "code", "type": "FUNCTION", "source_file": "Assets\\PlayFabSDK\\Groups\\PlayFabGroupsAPI.cs", "source_location": "L144", "complexity": 5, "loc": 9}, {"id": "playfabgroupsapi_playfabgroupsapi_deleterole", "label": ".DeleteRole()", "file_type": "code", "type": "FUNCTION", "source_file": "Assets\\PlayFabSDK\\Groups\\PlayFabGroupsAPI.cs", "source_location": "L157", "complexity": 5, "loc": 9}, {"id": "playfabgroupsapi_playfabgroupsapi_getgroup", "label": ".GetGroup()", "file_type": "code", "type": "FUNCTION", "source_file": "Assets\\PlayFabSDK\\Groups\\PlayFabGroupsAPI.cs", "source_location": "L170", "complexity": 5, "loc": 9}, {"id": "playfabgroupsapi_playfabgroupsapi_invitetogroup", "label": ".InviteToGroup()", "file_type": "code", "type": "FUNCTION", "source_file": "Assets\\PlayFabSDK\\Groups\\PlayFabGroupsAPI.cs", "source_location": "L183", "complexity": 5, "loc": 9}, {"id": "playfabgroupsapi_playfabgroupsapi_ismember", "label": ".IsMember()", "file_type": "code", "type": "FUNCTION", "source_file": "Assets\\PlayFabSDK\\Groups\\PlayFabGroupsAPI.cs", "source_location": "L196", "complexity": 5, "loc": 9}, {"id": "playfabgroupsapi_playfabgroupsapi_listgroupapplications", "label": ".ListGroupApplications()", "file_type": "code", "type": "FUNCTION", "source_file": "Assets\\PlayFabSDK\\Groups\\PlayFabGroupsAPI.cs", "source_location": "L209", "complexity": 5, "loc": 9}, {"id": "playfabgroupsapi_playfabgroupsapi_listgroupblocks", "label": ".ListGroupBlocks()", "file_type": "code", "type": "FUNCTION", "source_file": "Assets\\PlayFabSDK\\Groups\\PlayFabGroupsAPI.cs", "source_location": "L222", "complexity": 5, "loc": 9}, {"id": "playfabgroupsapi_playfabgroupsapi_listgroupinvitations", "label": ".ListGroupInvitations()", "file_type": "code", "type": "FUNCTION", "source_file": "Assets\\PlayFabSDK\\Groups\\PlayFabGroupsAPI.cs", "source_location": "L235", "complexity": 5, "loc": 9}, {"id": "playfabgroupsapi_playfabgroupsapi_listgroupmembers", "label": ".ListGroupMembers()", "file_type": "code", "type": "FUNCTION", "source_file": "Assets\\PlayFabSDK\\Groups\\PlayFabGroupsAPI.cs", "source_location": "L248", "complexity": 5, "loc": 9}, {"id": "playfabgroupsapi_playfabgroupsapi_listmembership", "label": ".ListMembership()", "file_type": "code", "type": "FUNCTION", "source_file": "Assets\\PlayFabSDK\\Groups\\PlayFabGroupsAPI.cs", "source_location": "L261", "complexity": 5, "loc": 9}, {"id": "playfabgroupsapi_playfabgroupsapi_listmembershipopportunities", "label": ".ListMembershipOpportunities()", "file_type": "code", "type": "FUNCTION", "source_file": "Assets\\PlayFabSDK\\Groups\\PlayFabGroupsAPI.cs", "source_location": "L274", "complexity": 5, "loc": 9}, {"id": "playfabgroupsapi_playfabgroupsapi_removegroupapplication", "label": ".RemoveGroupApplication()", "file_type": "code", "type": "FUNCTION", "source_file": "Assets\\PlayFabSDK\\Groups\\PlayFabGroupsAPI.cs", "source_location": "L287", "complexity": 5, "loc": 9}, {"id": "playfabgroupsapi_playfabgroupsapi_removegroupinvitation", "label": ".RemoveGroupInvitation()", "file_type": "code", "type": "FUNCTION", "source_file": "Assets\\PlayFabSDK\\Groups\\PlayFabGroupsAPI.cs", "source_location": "L300", "complexity": 5, "loc": 9}, {"id": "playfabgroupsapi_playfabgroupsapi_removemembers", "label": ".RemoveMembers()", "file_type": "code", "type": "FUNCTION", "source_file": "Assets\\PlayFabSDK\\Groups\\PlayFabGroupsAPI.cs", "source_location": "L313", "complexity": 5, "loc": 9}, {"id": "playfabgroupsapi_playfabgroupsapi_unblockentity", "label": ".UnblockEntity()", "file_type": "code", "type": "FUNCTION", "source_file": "Assets\\PlayFabSDK\\Groups\\PlayFabGroupsAPI.cs", "source_location": "L326", "complexity": 5, "loc": 9}, {"id": "playfabgroupsapi_playfabgroupsapi_updategroup", "label": ".UpdateGroup()", "file_type": "code", "type": "FUNCTION", "source_file": "Assets\\PlayFabSDK\\Groups\\PlayFabGroupsAPI.cs", "source_location": "L339", "complexity": 5, "loc": 9}, {"id": "playfabgroupsapi_playfabgroupsapi_updaterole", "label": ".UpdateRole()", "file_type": "code", "type": "FUNCTION", "source_file": "Assets\\PlayFabSDK\\Groups\\PlayFabGroupsAPI.cs", "source_location": "L352", "complexity": 5, "loc": 9}], "edges": [{"source": "assets_playfabsdk_groups_playfabgroupsapi_cs", "target": "system", "relation": "imports", "confidence": "EXTRACTED", "source_file": "Assets\\PlayFabSDK\\Groups\\PlayFabGroupsAPI.cs", "source_location": "L3", "weight": 1.0}, {"source": "assets_playfabsdk_groups_playfabgroupsapi_cs", "target": "generic", "relation": "imports", "confidence": "EXTRACTED", "source_file": "Assets\\PlayFabSDK\\Groups\\PlayFabGroupsAPI.cs", "source_location": "L4", "weight": 1.0}, {"source": "assets_playfabsdk_groups_playfabgroupsapi_cs", "target": "groupsmodels", "relation": "imports", "confidence": "EXTRACTED", "source_file": "Assets\\PlayFabSDK\\Groups\\PlayFabGroupsAPI.cs", "source_location": "L5", "weight": 1.0}, {"source": "assets_playfabsdk_groups_playfabgroupsapi_cs", "target": "internal", "relation": "imports", "confidence": "EXTRACTED", "source_file": "Assets\\PlayFabSDK\\Groups\\PlayFabGroupsAPI.cs", "source_location": "L6", "weight": 1.0}, {"source": "assets_playfabsdk_groups_playfabgroupsapi_cs", "target": "playfabgroupsapi_playfab", "relation": "contains", "confidence": "EXTRACTED", "source_file": "Assets\\PlayFabSDK\\Groups\\PlayFabGroupsAPI.cs", "source_location": "L8", "weight": 1.0}, {"source": "assets_playfabsdk_groups_playfabgroupsapi_cs", "target": "playfabgroupsapi_playfabgroupsapi", "relation": "contains", "confidence": "EXTRACTED", "source_file": "Assets\\PlayFabSDK\\Groups\\PlayFabGroupsAPI.cs", "source_location": "L15", "weight": 1.0}, {"source": "playfabgroupsapi_playfabgroupsapi", "target": "playfabgroupsapi_playfabgroupsapi_isentityloggedin", "relation": "method", "confidence": "EXTRACTED", "source_file": "Assets\\PlayFabSDK\\Groups\\PlayFabGroupsAPI.cs", "source_location": "L23", "weight": 1.0}, {"source": "playfabgroupsapi_playfabgroupsapi", "target": "playfabgroupsapi_playfabgroupsapi_forgetallcredentials", "relation": "method", "confidence": "EXTRACTED", "source_file": "Assets\\PlayFabSDK\\Groups\\PlayFabGroupsAPI.cs", "source_location": "L32", "weight": 1.0}, {"source": "playfabgroupsapi_playfabgroupsapi", "target": "playfabgroupsapi_playfabgroupsapi_acceptgroupapplication", "relation": "method", "confidence": "EXTRACTED", "source_file": "Assets\\PlayFabSDK\\Groups\\PlayFabGroupsAPI.cs", "source_location": "L40", "weight": 1.0}, {"source": "playfabgroupsapi_playfabgroupsapi", "target": "playfabgroupsapi_playfabgroupsapi_acceptgroupinvitation", "relation": "method", "confidence": "EXTRACTED", "source_file": "Assets\\PlayFabSDK\\Groups\\PlayFabGroupsAPI.cs", "source_location": "L53", "weight": 1.0}, {"source": "playfabgroupsapi_playfabgroupsapi", "target": "playfabgroupsapi_playfabgroupsapi_addmembers", "relation": "method", "confidence": "EXTRACTED", "source_file": "Assets\\PlayFabSDK\\Groups\\PlayFabGroupsAPI.cs", "source_location": "L66", "weight": 1.0}, {"source": "playfabgroupsapi_playfabgroupsapi", "target": "playfabgroupsapi_playfabgroupsapi_applytogroup", "relation": "method", "confidence": "EXTRACTED", "source_file": "Assets\\PlayFabSDK\\Groups\\PlayFabGroupsAPI.cs", "source_location": "L79", "weight": 1.0}, {"source": "playfabgroupsapi_playfabgroupsapi", "target": "playfabgroupsapi_playfabgroupsapi_blockentity", "relation": "method", "confidence": "EXTRACTED", "source_file": "Assets\\PlayFabSDK\\Groups\\PlayFabGroupsAPI.cs", "source_location": "L92", "weight": 1.0}, {"source": "playfabgroupsapi_playfabgroupsapi", "target": "playfabgroupsapi_playfabgroupsapi_changememberrole", "relation": "method", "confidence": "EXTRACTED", "source_file": "Assets\\PlayFabSDK\\Groups\\PlayFabGroupsAPI.cs", "source_location": "L105", "weight": 1.0}, {"source": "playfabgroupsapi_playfabgroupsapi", "target": "playfabgroupsapi_playfabgroupsapi_creategroup", "relation": "method", "confidence": "EXTRACTED", "source_file": "Assets\\PlayFabSDK\\Groups\\PlayFabGroupsAPI.cs", "source_location": "L118", "weight": 1.0}, {"source": "playfabgroupsapi_playfabgroupsapi", "target": "playfabgroupsapi_playfabgroupsapi_createrole", "relation": "method", "confidence": "EXTRACTED", "source_file": "Assets\\PlayFabSDK\\Groups\\PlayFabGroupsAPI.cs", "source_location": "L131", "weight": 1.0}, {"source": "playfabgroupsapi_playfabgroupsapi", "target": "playfabgroupsapi_playfabgroupsapi_deletegroup", "relation": "method", "confidence": "EXTRACTED", "source_file": "Assets\\PlayFabSDK\\Groups\\PlayFabGroupsAPI.cs", "source_location": "L144", "weight": 1.0}, {"source": "playfabgroupsapi_playfabgroupsapi", "target": "playfabgroupsapi_playfabgroupsapi_deleterole", "relation": "method", "confidence": "EXTRACTED", "source_file": "Assets\\PlayFabSDK\\Groups\\PlayFabGroupsAPI.cs", "source_location": "L157", "weight": 1.0}, {"source": "playfabgroupsapi_playfabgroupsapi", "target": "playfabgroupsapi_playfabgroupsapi_getgroup", "relation": "method", "confidence": "EXTRACTED", "source_file": "Assets\\PlayFabSDK\\Groups\\PlayFabGroupsAPI.cs", "source_location": "L170", "weight": 1.0}, {"source": "playfabgroupsapi_playfabgroupsapi", "target": "playfabgroupsapi_playfabgroupsapi_invitetogroup", "relation": "method", "confidence": "EXTRACTED", "source_file": "Assets\\PlayFabSDK\\Groups\\PlayFabGroupsAPI.cs", "source_location": "L183", "weight": 1.0}, {"source": "playfabgroupsapi_playfabgroupsapi", "target": "playfabgroupsapi_playfabgroupsapi_ismember", "relation": "method", "confidence": "EXTRACTED", "source_file": "Assets\\PlayFabSDK\\Groups\\PlayFabGroupsAPI.cs", "source_location": "L196", "weight": 1.0}, {"source": "playfabgroupsapi_playfabgroupsapi", "target": "playfabgroupsapi_playfabgroupsapi_listgroupapplications", "relation": "method", "confidence": "EXTRACTED", "source_file": "Assets\\PlayFabSDK\\Groups\\PlayFabGroupsAPI.cs", "source_location": "L209", "weight": 1.0}, {"source": "playfabgroupsapi_playfabgroupsapi", "target": "playfabgroupsapi_playfabgroupsapi_listgroupblocks", "relation": "method", "confidence": "EXTRACTED", "source_file": "Assets\\PlayFabSDK\\Groups\\PlayFabGroupsAPI.cs", "source_location": "L222", "weight": 1.0}, {"source": "playfabgroupsapi_playfabgroupsapi", "target": "playfabgroupsapi_playfabgroupsapi_listgroupinvitations", "relation": "method", "confidence": "EXTRACTED", "source_file": "Assets\\PlayFabSDK\\Groups\\PlayFabGroupsAPI.cs", "source_location": "L235", "weight": 1.0}, {"source": "playfabgroupsapi_playfabgroupsapi", "target": "playfabgroupsapi_playfabgroupsapi_listgroupmembers", "relation": "method", "confidence": "EXTRACTED", "source_file": "Assets\\PlayFabSDK\\Groups\\PlayFabGroupsAPI.cs", "source_location": "L248", "weight": 1.0}, {"source": "playfabgroupsapi_playfabgroupsapi", "target": "playfabgroupsapi_playfabgroupsapi_listmembership", "relation": "method", "confidence": "EXTRACTED", "source_file": "Assets\\PlayFabSDK\\Groups\\PlayFabGroupsAPI.cs", "source_location": "L261", "weight": 1.0}, {"source": "playfabgroupsapi_playfabgroupsapi", "target": "playfabgroupsapi_playfabgroupsapi_listmembershipopportunities", "relation": "method", "confidence": "EXTRACTED", "source_file": "Assets\\PlayFabSDK\\Groups\\PlayFabGroupsAPI.cs", "source_location": "L274", "weight": 1.0}, {"source": "playfabgroupsapi_playfabgroupsapi", "target": "playfabgroupsapi_playfabgroupsapi_removegroupapplication", "relation": "method", "confidence": "EXTRACTED", "source_file": "Assets\\PlayFabSDK\\Groups\\PlayFabGroupsAPI.cs", "source_location": "L287", "weight": 1.0}, {"source": "playfabgroupsapi_playfabgroupsapi", "target": "playfabgroupsapi_playfabgroupsapi_removegroupinvitation", "relation": "method", "confidence": "EXTRACTED", "source_file": "Assets\\PlayFabSDK\\Groups\\PlayFabGroupsAPI.cs", "source_location": "L300", "weight": 1.0}, {"source": "playfabgroupsapi_playfabgroupsapi", "target": "playfabgroupsapi_playfabgroupsapi_removemembers", "relation": "method", "confidence": "EXTRACTED", "source_file": "Assets\\PlayFabSDK\\Groups\\PlayFabGroupsAPI.cs", "source_location": "L313", "weight": 1.0}, {"source": "playfabgroupsapi_playfabgroupsapi", "target": "playfabgroupsapi_playfabgroupsapi_unblockentity", "relation": "method", "confidence": "EXTRACTED", "source_file": "Assets\\PlayFabSDK\\Groups\\PlayFabGroupsAPI.cs", "source_location": "L326", "weight": 1.0}, {"source": "playfabgroupsapi_playfabgroupsapi", "target": "playfabgroupsapi_playfabgroupsapi_updategroup", "relation": "method", "confidence": "EXTRACTED", "source_file": "Assets\\PlayFabSDK\\Groups\\PlayFabGroupsAPI.cs", "source_location": "L339", "weight": 1.0}, {"source": "playfabgroupsapi_playfabgroupsapi", "target": "playfabgroupsapi_playfabgroupsapi_updaterole", "relation": "method", "confidence": "EXTRACTED", "source_file": "Assets\\PlayFabSDK\\Groups\\PlayFabGroupsAPI.cs", "source_location": "L352", "weight": 1.0}, {"source": "playfabgroupsapi_playfabgroupsapi_acceptgroupapplication", "target": "playfabgroupsapi_playfabgroupsapi_isentityloggedin", "relation": "calls", "confidence": "EXTRACTED", "source_file": "Assets\\PlayFabSDK\\Groups\\PlayFabGroupsAPI.cs", "source_location": "L44", "weight": 1.0}, {"source": "playfabgroupsapi_playfabgroupsapi_acceptgroupinvitation", "target": "playfabgroupsapi_playfabgroupsapi_isentityloggedin", "relation": "calls", "confidence": "EXTRACTED", "source_file": "Assets\\PlayFabSDK\\Groups\\PlayFabGroupsAPI.cs", "source_location": "L57", "weight": 1.0}, {"source": "playfabgroupsapi_playfabgroupsapi_addmembers", "target": "playfabgroupsapi_playfabgroupsapi_isentityloggedin", "relation": "calls", "confidence": "EXTRACTED", "source_file": "Assets\\PlayFabSDK\\Groups\\PlayFabGroupsAPI.cs", "source_location": "L70", "weight": 1.0}, {"source": "playfabgroupsapi_playfabgroupsapi_applytogroup", "target": "playfabgroupsapi_playfabgroupsapi_isentityloggedin", "relation": "calls", "confidence": "EXTRACTED", "source_file": "Assets\\PlayFabSDK\\Groups\\PlayFabGroupsAPI.cs", "source_location": "L83", "weight": 1.0}, {"source": "playfabgroupsapi_playfabgroupsapi_blockentity", "target": "playfabgroupsapi_playfabgroupsapi_isentityloggedin", "relation": "calls", "confidence": "EXTRACTED", "source_file": "Assets\\PlayFabSDK\\Groups\\PlayFabGroupsAPI.cs", "source_location": "L96", "weight": 1.0}, {"source": "playfabgroupsapi_playfabgroupsapi_changememberrole", "target": "playfabgroupsapi_playfabgroupsapi_isentityloggedin", "relation": "calls", "confidence": "EXTRACTED", "source_file": "Assets\\PlayFabSDK\\Groups\\PlayFabGroupsAPI.cs", "source_location": "L109", "weight": 1.0}, {"source": "playfabgroupsapi_playfabgroupsapi_creategroup", "target": "playfabgroupsapi_playfabgroupsapi_isentityloggedin", "relation": "calls", "confidence": "EXTRACTED", "source_file": "Assets\\PlayFabSDK\\Groups\\PlayFabGroupsAPI.cs", "source_location": "L122", "weight": 1.0}, {"source": "playfabgroupsapi_playfabgroupsapi_createrole", "target": "playfabgroupsapi_playfabgroupsapi_isentityloggedin", "relation": "calls", "confidence": "EXTRACTED", "source_file": "Assets\\PlayFabSDK\\Groups\\PlayFabGroupsAPI.cs", "source_location": "L135", "weight": 1.0}, {"source": "playfabgroupsapi_playfabgroupsapi_deletegroup", "target": "playfabgroupsapi_playfabgroupsapi_isentityloggedin", "relation": "calls", "confidence": "EXTRACTED", "source_file": "Assets\\PlayFabSDK\\Groups\\PlayFabGroupsAPI.cs", "source_location": "L148", "weight": 1.0}, {"source": "playfabgroupsapi_playfabgroupsapi_deleterole", "target": "playfabgroupsapi_playfabgroupsapi_isentityloggedin", "relation": "calls", "confidence": "EXTRACTED", "source_file": "Assets\\PlayFabSDK\\Groups\\PlayFabGroupsAPI.cs", "source_location": "L161", "weight": 1.0}, {"source": "playfabgroupsapi_playfabgroupsapi_getgroup", "target": "playfabgroupsapi_playfabgroupsapi_isentityloggedin", "relation": "calls", "confidence": "EXTRACTED", "source_file": "Assets\\PlayFabSDK\\Groups\\PlayFabGroupsAPI.cs", "source_location": "L174", "weight": 1.0}, {"source": "playfabgroupsapi_playfabgroupsapi_invitetogroup", "target": "playfabgroupsapi_playfabgroupsapi_isentityloggedin", "relation": "calls", "confidence": "EXTRACTED", "source_file": "Assets\\PlayFabSDK\\Groups\\PlayFabGroupsAPI.cs", "source_location": "L187", "weight": 1.0}, {"source": "playfabgroupsapi_playfabgroupsapi_ismember", "target": "playfabgroupsapi_playfabgroupsapi_isentityloggedin", "relation": "calls", "confidence": "EXTRACTED", "source_file": "Assets\\PlayFabSDK\\Groups\\PlayFabGroupsAPI.cs", "source_location": "L200", "weight": 1.0}, {"source": "playfabgroupsapi_playfabgroupsapi_listgroupapplications", "target": "playfabgroupsapi_playfabgroupsapi_isentityloggedin", "relation": "calls", "confidence": "EXTRACTED", "source_file": "Assets\\PlayFabSDK\\Groups\\PlayFabGroupsAPI.cs", "source_location": "L213", "weight": 1.0}, {"source": "playfabgroupsapi_playfabgroupsapi_listgroupblocks", "target": "playfabgroupsapi_playfabgroupsapi_isentityloggedin", "relation": "calls", "confidence": "EXTRACTED", "source_file": "Assets\\PlayFabSDK\\Groups\\PlayFabGroupsAPI.cs", "source_location": "L226", "weight": 1.0}, {"source": "playfabgroupsapi_playfabgroupsapi_listgroupinvitations", "target": "playfabgroupsapi_playfabgroupsapi_isentityloggedin", "relation": "calls", "confidence": "EXTRACTED", "source_file": "Assets\\PlayFabSDK\\Groups\\PlayFabGroupsAPI.cs", "source_location": "L239", "weight": 1.0}, {"source": "playfabgroupsapi_playfabgroupsapi_listgroupmembers", "target": "playfabgroupsapi_playfabgroupsapi_isentityloggedin", "relation": "calls", "confidence": "EXTRACTED", "source_file": "Assets\\PlayFabSDK\\Groups\\PlayFabGroupsAPI.cs", "source_location": "L252", "weight": 1.0}, {"source": "playfabgroupsapi_playfabgroupsapi_listmembership", "target": "playfabgroupsapi_playfabgroupsapi_isentityloggedin", "relation": "calls", "confidence": "EXTRACTED", "source_file": "Assets\\PlayFabSDK\\Groups\\PlayFabGroupsAPI.cs", "source_location": "L265", "weight": 1.0}, {"source": "playfabgroupsapi_playfabgroupsapi_listmembershipopportunities", "target": "playfabgroupsapi_playfabgroupsapi_isentityloggedin", "relation": "calls", "confidence": "EXTRACTED", "source_file": "Assets\\PlayFabSDK\\Groups\\PlayFabGroupsAPI.cs", "source_location": "L278", "weight": 1.0}, {"source": "playfabgroupsapi_playfabgroupsapi_removegroupapplication", "target": "playfabgroupsapi_playfabgroupsapi_isentityloggedin", "relation": "calls", "confidence": "EXTRACTED", "source_file": "Assets\\PlayFabSDK\\Groups\\PlayFabGroupsAPI.cs", "source_location": "L291", "weight": 1.0}, {"source": "playfabgroupsapi_playfabgroupsapi_removegroupinvitation", "target": "playfabgroupsapi_playfabgroupsapi_isentityloggedin", "relation": "calls", "confidence": "EXTRACTED", "source_file": "Assets\\PlayFabSDK\\Groups\\PlayFabGroupsAPI.cs", "source_location": "L304", "weight": 1.0}, {"source": "playfabgroupsapi_playfabgroupsapi_removemembers", "target": "playfabgroupsapi_playfabgroupsapi_isentityloggedin", "relation": "calls", "confidence": "EXTRACTED", "source_file": "Assets\\PlayFabSDK\\Groups\\PlayFabGroupsAPI.cs", "source_location": "L317", "weight": 1.0}, {"source": "playfabgroupsapi_playfabgroupsapi_unblockentity", "target": "playfabgroupsapi_playfabgroupsapi_isentityloggedin", "relation": "calls", "confidence": "EXTRACTED", "source_file": "Assets\\PlayFabSDK\\Groups\\PlayFabGroupsAPI.cs", "source_location": "L330", "weight": 1.0}, {"source": "playfabgroupsapi_playfabgroupsapi_updategroup", "target": "playfabgroupsapi_playfabgroupsapi_isentityloggedin", "relation": "calls", "confidence": "EXTRACTED", "source_file": "Assets\\PlayFabSDK\\Groups\\PlayFabGroupsAPI.cs", "source_location": "L343", "weight": 1.0}, {"source": "playfabgroupsapi_playfabgroupsapi_updaterole", "target": "playfabgroupsapi_playfabgroupsapi_isentityloggedin", "relation": "calls", "confidence": "EXTRACTED", "source_file": "Assets\\PlayFabSDK\\Groups\\PlayFabGroupsAPI.cs", "source_location": "L356", "weight": 1.0}], "raw_calls": [{"caller_nid": "playfabgroupsapi_playfabgroupsapi_acceptgroupapplication", "callee": "MakeApiCall", "source_file": "Assets\\PlayFabSDK\\Groups\\PlayFabGroupsAPI.cs", "source_location": "L47"}, {"caller_nid": "playfabgroupsapi_playfabgroupsapi_acceptgroupinvitation", "callee": "MakeApiCall", "source_file": "Assets\\PlayFabSDK\\Groups\\PlayFabGroupsAPI.cs", "source_location": "L60"}, {"caller_nid": "playfabgroupsapi_playfabgroupsapi_addmembers", "callee": "MakeApiCall", "source_file": "Assets\\PlayFabSDK\\Groups\\PlayFabGroupsAPI.cs", "source_location": "L73"}, {"caller_nid": "playfabgroupsapi_playfabgroupsapi_applytogroup", "callee": "MakeApiCall", "source_file": "Assets\\PlayFabSDK\\Groups\\PlayFabGroupsAPI.cs", "source_location": "L86"}, {"caller_nid": "playfabgroupsapi_playfabgroupsapi_blockentity", "callee": "MakeApiCall", "source_file": "Assets\\PlayFabSDK\\Groups\\PlayFabGroupsAPI.cs", "source_location": "L99"}, {"caller_nid": "playfabgroupsapi_playfabgroupsapi_changememberrole", "callee": "MakeApiCall", "source_file": "Assets\\PlayFabSDK\\Groups\\PlayFabGroupsAPI.cs", "source_location": "L112"}, {"caller_nid": "playfabgroupsapi_playfabgroupsapi_creategroup", "callee": "MakeApiCall", "source_file": "Assets\\PlayFabSDK\\Groups\\PlayFabGroupsAPI.cs", "source_location": "L125"}, {"caller_nid": "playfabgroupsapi_playfabgroupsapi_createrole", "callee": "MakeApiCall", "source_file": "Assets\\PlayFabSDK\\Groups\\PlayFabGroupsAPI.cs", "source_location": "L138"}, {"caller_nid": "playfabgroupsapi_playfabgroupsapi_deletegroup", "callee": "MakeApiCall", "source_file": "Assets\\PlayFabSDK\\Groups\\PlayFabGroupsAPI.cs", "source_location": "L151"}, {"caller_nid": "playfabgroupsapi_playfabgroupsapi_deleterole", "callee": "MakeApiCall", "source_file": "Assets\\PlayFabSDK\\Groups\\PlayFabGroupsAPI.cs", "source_location": "L164"}, {"caller_nid": "playfabgroupsapi_playfabgroupsapi_getgroup", "callee": "MakeApiCall", "source_file": "Assets\\PlayFabSDK\\Groups\\PlayFabGroupsAPI.cs", "source_location": "L177"}, {"caller_nid": "playfabgroupsapi_playfabgroupsapi_invitetogroup", "callee": "MakeApiCall", "source_file": "Assets\\PlayFabSDK\\Groups\\PlayFabGroupsAPI.cs", "source_location": "L190"}, {"caller_nid": "playfabgroupsapi_playfabgroupsapi_ismember", "callee": "MakeApiCall", "source_file": "Assets\\PlayFabSDK\\Groups\\PlayFabGroupsAPI.cs", "source_location": "L203"}, {"caller_nid": "playfabgroupsapi_playfabgroupsapi_listgroupapplications", "callee": "MakeApiCall", "source_file": "Assets\\PlayFabSDK\\Groups\\PlayFabGroupsAPI.cs", "source_location": "L216"}, {"caller_nid": "playfabgroupsapi_playfabgroupsapi_listgroupblocks", "callee": "MakeApiCall", "source_file": "Assets\\PlayFabSDK\\Groups\\PlayFabGroupsAPI.cs", "source_location": "L229"}, {"caller_nid": "playfabgroupsapi_playfabgroupsapi_listgroupinvitations", "callee": "MakeApiCall", "source_file": "Assets\\PlayFabSDK\\Groups\\PlayFabGroupsAPI.cs", "source_location": "L242"}, {"caller_nid": "playfabgroupsapi_playfabgroupsapi_listgroupmembers", "callee": "MakeApiCall", "source_file": "Assets\\PlayFabSDK\\Groups\\PlayFabGroupsAPI.cs", "source_location": "L255"}, {"caller_nid": "playfabgroupsapi_playfabgroupsapi_listmembership", "callee": "MakeApiCall", "source_file": "Assets\\PlayFabSDK\\Groups\\PlayFabGroupsAPI.cs", "source_location": "L268"}, {"caller_nid": "playfabgroupsapi_playfabgroupsapi_listmembershipopportunities", "callee": "MakeApiCall", "source_file": "Assets\\PlayFabSDK\\Groups\\PlayFabGroupsAPI.cs", "source_location": "L281"}, {"caller_nid": "playfabgroupsapi_playfabgroupsapi_removegroupapplication", "callee": "MakeApiCall", "source_file": "Assets\\PlayFabSDK\\Groups\\PlayFabGroupsAPI.cs", "source_location": "L294"}, {"caller_nid": "playfabgroupsapi_playfabgroupsapi_removegroupinvitation", "callee": "MakeApiCall", "source_file": "Assets\\PlayFabSDK\\Groups\\PlayFabGroupsAPI.cs", "source_location": "L307"}, {"caller_nid": "playfabgroupsapi_playfabgroupsapi_removemembers", "callee": "MakeApiCall", "source_file": "Assets\\PlayFabSDK\\Groups\\PlayFabGroupsAPI.cs", "source_location": "L320"}, {"caller_nid": "playfabgroupsapi_playfabgroupsapi_unblockentity", "callee": "MakeApiCall", "source_file": "Assets\\PlayFabSDK\\Groups\\PlayFabGroupsAPI.cs", "source_location": "L333"}, {"caller_nid": "playfabgroupsapi_playfabgroupsapi_updategroup", "callee": "MakeApiCall", "source_file": "Assets\\PlayFabSDK\\Groups\\PlayFabGroupsAPI.cs", "source_location": "L346"}, {"caller_nid": "playfabgroupsapi_playfabgroupsapi_updaterole", "callee": "MakeApiCall", "source_file": "Assets\\PlayFabSDK\\Groups\\PlayFabGroupsAPI.cs", "source_location": "L359"}]}